opendata_finance_kr/__init__.py
opendata_finance_kr/clients.py
opendata_finance_kr/tools/__init__.py
opendata_finance_kr/tools/backtester.py
opendata_finance_kr/tools/screener.py
opendata_finance_kr/tools/types.py
opendata_finance_kr-0.1.6.dist-info/METADATA
opendata_finance_kr-0.1.6.dist-info/WHEEL
opendata_finance_kr-0.1.6.dist-info/licenses/LICENSE
opendata_finance_kr-0.1.6.dist-info/RECORD
