Metadata-Version: 2.1
Name: opendata_finance_kr
Version: 0.1.6
Summary: A package for opendata-finance-kr
Project-URL: Homepage, https://github.com/ghkim9213/opendata-finance-kr-client
Project-URL: Bug Tracker, https://github.com/ghkim9213/opendata-finance-kr-client/issues
Author-email: ghkim <ghkim9213@gmail.com>
License-File: LICENSE
Classifier: License :: OSI Approved :: MIT License
Classifier: Operating System :: OS Independent
Classifier: Programming Language :: Python :: 3
Requires-Python: >=3.7
Requires-Dist: matplotlib>=3.2.2
Requires-Dist: pandas>=1.3.5
Requires-Dist: requests>=2.25.1
